cfdi_to_xml/__init__.py
cfdi_to_xml/cfdv40/__init__.py
cfdi_to_xml/cfdv40/c_estado.py
cfdi_to_xml/cfdv40/c_exportacion.py
cfdi_to_xml/cfdv40/c_forma_pago.py
cfdi_to_xml/cfdv40/c_impuesto.py
cfdi_to_xml/cfdv40/c_meses.py
cfdi_to_xml/cfdv40/c_metodo_pago.py
cfdi_to_xml/cfdv40/c_moneda.py
cfdi_to_xml/cfdv40/c_objeto_imp.py
cfdi_to_xml/cfdv40/c_pais.py
cfdi_to_xml/cfdv40/c_periodicidad.py
cfdi_to_xml/cfdv40/c_regimen_fiscal.py
cfdi_to_xml/cfdv40/c_tipo_de_comprobante.py
cfdi_to_xml/cfdv40/c_tipo_factor.py
cfdi_to_xml/cfdv40/c_tipo_relacion.py
cfdi_to_xml/cfdv40/c_uso_cfdi.py
cfdi_to_xml/cfdv40/comprobante.py
cfdi_to_xml-0.0.4.dist-info/LICENSE
cfdi_to_xml-0.0.4.dist-info/WHEEL
cfdi_to_xml-0.0.4.dist-info/METADATA
cfdi_to_xml-0.0.4.dist-info/RECORD
