Metadata-Version: 2.1
Name: cfdi-to-xml
Version: 0.0.4
Summary: Library to create XML fiel from CFDI representation.
License: LGPL-2.1
Author: Moises Navarro
Author-email: moisalejandro@gmail.com
Requires-Python: >=3.7,<4.0
Classifier: License :: OSI Approved
Classifier: Programming Language :: Python :: 3
Classifier: Programming Language :: Python :: 3.10
Classifier: Programming Language :: Python :: 3.7
Classifier: Programming Language :: Python :: 3.8
Classifier: Programming Language :: Python :: 3.9
Requires-Dist: lxml (>=4.8.0,<5.0.0)
Requires-Dist: requests (>=2.27.1,<3.0.0)
Requires-Dist: xsdata (>=22.4,<23.0)
